paddletools/__init__.py
paddletools/checkpoints.py
paddletools/config.py
paddletools/control.py
paddletools/__pycache__/__init__.cpython-36.pyc
paddletools/__pycache__/config.cpython-36.pyc
paddletools/reminder/__init__.py
paddletools/reminder/email.py
paddletools/reminder/wechat.py
paddletools/reminder/__pycache__/__init__.cpython-36.pyc
paddletools/reminder/__pycache__/email.cpython-36.pyc
paddletools/utils/__init__.py
paddletools/utils/decoder.py
paddletools/utils/encoder.py
paddletools/utils/logger.py
paddletools/utils/__pycache__/__init__.cpython-36.pyc
paddletools/utils/__pycache__/logger.cpython-36.pyc
paddletools-0.0.5.dist-info/METADATA
paddletools-0.0.5.dist-info/RECORD
paddletools-0.0.5.dist-info/WHEEL
paddletools-0.0.5.dist-info/entry_points.txt
paddletools-0.0.5.dist-info/top_level.txt
